sli_lib-0.2.4.data/platlib/sli_lib/README.md
sli_lib-0.2.4.dist-info/METADATA
sli_lib-0.2.4.dist-info/WHEEL
sli_lib-0.2.4.dist-info/entry_points.txt
sli_lib-0.2.4.dist-info/licenses/LICENSE
sli_lib/__init__.py
sli_lib/__init__.pyi
sli_lib/__main__.py
sli_lib/_all_utils.py
sli_lib/fodot/__init__.py
sli_lib/fodot/collections/__init__.py
sli_lib/fodot/collections/set/__init__.py
sli_lib/fodot/collections/set/__init__.pyi
sli_lib/fodot/collections/set/py.typed
sli_lib/fodot/knowledge_base/__init__.py
sli_lib/fodot/knowledge_base/__init__.pyi
sli_lib/fodot/knowledge_base/_pure.py
sli_lib/fodot/knowledge_base/py.typed
sli_lib/fodot/structure/__init__.py
sli_lib/fodot/structure/__init__.pyi
sli_lib/fodot/structure/_pure.py
sli_lib/fodot/structure/py.typed
sli_lib/fodot/theory/__init__.py
sli_lib/fodot/theory/__init__.pyi
sli_lib/fodot/theory/py.typed
sli_lib/fodot/vocabulary/__init__.py
sli_lib/fodot/vocabulary/__init__.pyi
sli_lib/fodot/vocabulary/_pure.py
sli_lib/fodot/vocabulary/py.typed
sli_lib/methods.py
sli_lib/py.typed
sli_lib/sli_lib.abi3.so
sli_lib/solver/__init__.py
sli_lib/solver/__init__.pyi
sli_lib/solver/_pure.py
sli_lib/solver/py.typed
sli_lib-0.2.4.dist-info/RECORD
