Metadata-Version: 2.4
Name: sli-lib
Version: 0.2.4
Requires-Dist: mypy>=1.15 ; extra == 'dev'
Requires-Dist: pytest>=8.3 ; extra == 'dev'
Requires-Dist: pdoc>=15 ; extra == 'dev'
Provides-Extra: dev
License-File: LICENSE
Summary: Python api for the sli-lib Rust library
Home-Page: https://gitlab.com/sli-lib/SLI
License: LGPL-3.0-or-later
Requires-Python: >=3.11
Project-URL: homepage, https://gitlab.com/sli-lib/SLI
Project-URL: documentation, https://sli-lib.gitlab.io/sli/python
Project-URL: repository, https://gitlab.com/sli-lib/SLI
Project-URL: download, https://pypi.org/project/sli-lib/#files
